dearning/AI_core.py
dearning/AI_tools.py
dearning/Quantum.py
dearning/__init__.py
dearning/__main__.py
dearning/model.py
dearning/service.py
dearning/training.py
dearning/utils.py
dearning-1.2.4.dist-info/METADATA
dearning-1.2.4.dist-info/WHEEL
dearning-1.2.4.dist-info/entry_points.txt
dearning-1.2.4.dist-info/top_level.txt
dearning-1.2.4.dist-info/RECORD
