Metadata-Version: 2.4
Name: dearning
Version: 1.2.4
Summary: Libraries untuk membuat AI yang ringan
Author: Oriza
License: Apache-2.0
Project-URL: Homepage, https://github.com/maker-games
Project-URL: Discussion, https://github.com/maker-games/Dearning/discussions/1
Project-URL: Tutorial, https://github.com/maker-games/Dearning/blob/main/tutorial-dearning
Classifier: Programming Language :: Python :: 3
Classifier: License :: OSI Approved :: Apache Software License
Classifier: Operating System :: OS Independent
Requires-Python: >=3.4
